{"features": [{"geometry": {"coordinates": [[[-87.43, 30.5], [-87.17, 30.52], [-87.14, 30.51], [-87.14, 30.45], [-87.3, 30.44], [-87.4, 30.43], [-87.4, 30.44], [-87.39, 30.45], [-87.4, 30.45], [-87.41, 30.45], [-87.42, 30.45], [-87.42, 30.46], [-87.43, 30.49], [-87.43, 30.5]]], "type": "Polygon"}, "properties": {"CAP_ID": "urn:oid:2.49.0.1.840.0.900d9da1ff3c67ad8892152e12c8cc94d24dae38.001.1", "ENDS": "2025-10-27T03:45:00-05:00", "EVENT": "0034", "EXPIRATION": "2025-10-27T03:45:00-05:00", "ISSUANCE": "2025-10-27T00:37:00-05:00", "MSG_TYPE": "FFW", "ONSET": "2025-10-27T00:37:00-05:00", "PHENOM": "FF", "PROD_TYPE": "Flash Flood Warning", "SIG": "W", "URL": "https://alerts.weather.gov/search?id=urn:oid:2.49.0.1.840.0.900d9da1ff3c67ad8892152e12c8cc94d24dae38.001.1", "VTEC": "/O.NEW.KMOB.FF.W.0034.251027T0537Z-251027T0845Z/", "WFO": "KMOB"}, "type": "Feature"}, {"geometry": {"coordinates": [[[-87.43, 30.55], [-87.41, 30.58], [-87.38, 30.59], [-87.29, 30.59], [-87.22, 30.58], [-87.22, 30.57], [-87.21, 30.56], [-87.15, 30.51], [-87.41, 30.49], [-87.44, 30.5], [-87.45, 30.51], [-87.43, 30.55]]], "type": "Polygon"}, "properties": {"CAP_ID": "urn:oid:2.49.0.1.840.0.ac8ed9de34919e0b05dce95ab6e2871ab6926ac6.001.1", "ENDS": "2025-10-27T03:00:00-05:00", "EVENT": "0033", "EXPIRATION": "2025-10-27T03:00:00-05:00", "ISSUANCE": "2025-10-26T23:59:00-05:00", "MSG_TYPE": "FFW", "ONSET": "2025-10-26T23:59:00-05:00", "PHENOM": "FF", "PROD_TYPE": "Flash Flood Warning", "SIG": "W", "URL": "https://alerts.weather.gov/search?id=urn:oid:2.49.0.1.840.0.ac8ed9de34919e0b05dce95ab6e2871ab6926ac6.001.1", "VTEC": "/O.NEW.KMOB.FF.W.0033.251027T0459Z-251027T0800Z/", "WFO": "KMOB"}, "type": "Feature"}, {"geometry": {"coordinates": [[[-86.98, 30.62], [-86.97, 30.51], [-86.84, 30.43], [-86.68, 30.43], [-86.57, 30.5], [-86.87, 30.04], [-87.78, 30.02], [-87.63, 30.39], [-87.49, 30.4], [-87.45, 30.54], [-87.3, 30.44], [-87.39, 30.36], [-87.23, 30.43], [-87.24, 30.48], [-87.19, 30.49], [-87.28, 30.63], [-87.2, 30.63], [-87.06, 30.55], [-87.09, 30.61], [-86.98, 30.62]]], "type": "Polygon"}, "properties": {"CAP_ID": "urn:oid:2.49.0.1.840.0.9e3a1424d84a69aa1bc65c29556e3e46ba648e4e.001.1", "ENDS": "2025-10-27T02:00:00-05:00", "EVENT": "0212", "EXPIRATION": "2025-10-27T02:00:00-05:00", "ISSUANCE": "2025-10-26T23:56:00-05:00", "MSG_TYPE": "SMW", "ONSET": "2025-10-26T23:56:00-05:00", "PHENOM": "MA", "PROD_TYPE": "Special Marine Warning", "SIG": "W", "URL": "https://alerts.weather.gov/search?id=urn:oid:2.49.0.1.840.0.9e3a1424d84a69aa1bc65c29556e3e46ba648e4e.001.1", "VTEC": "/O.NEW.KMOB.MA.W.0212.251027T0456Z-251027T0700Z/", "WFO": "KMOB"}, "type": "Feature"}, {"geometry": {"coordinates": [[[-87.61, 30.6], [-87.52, 30.58], [-87.52, 30.51], [-87.53, 30.51], [-87.69, 30.49], [-87.72, 30.49], [-87.73, 30.58], [-87.61, 30.6]]], "type": "Polygon"}, "properties": {"CAP_ID": "urn:oid:2.49.0.1.840.0.d5ac575199ff482fa3d43a3a5634c50564969596.001.1", "ENDS": "2025-10-27T03:00:00-05:00", "EVENT": "0032", "EXPIRATION": "2025-10-27T03:00:00-05:00", "ISSUANCE": "2025-10-26T23:54:00-05:00", "MSG_TYPE": "FFW", "ONSET": "2025-10-26T23:54:00-05:00", "PHENOM": "FF", "PROD_TYPE": "Flash Flood Warning", "SIG": "W", "URL": "https://alerts.weather.gov/search?id=urn:oid:2.49.0.1.840.0.d5ac575199ff482fa3d43a3a5634c50564969596.001.1", "VTEC": "/O.NEW.KMOB.FF.W.0032.251027T0454Z-251027T0800Z/", "WFO": "KMOB"}, "type": "Feature"}], "type": "FeatureCollection"}
