{"features": [{"geometry": {"coordinates": [[[-83.83, 30.04], [-83.75, 30.04], [-83.56, 29.86], [-83.65, 29.81], [-84.06, 29.74], [-84.08, 29.67], [-84.1, 29.65], [-84.2, 29.59], [-84.31, 29.56], [-84.6, 29.9], [-84.49, 29.96], [-84.43, 30.05], [-84.25, 30.15], [-84.1, 30.13], [-84.01, 30.17], [-83.83, 30.04]]], "type": "Polygon"}, "properties": {"CAP_ID": "urn:oid:2.49.0.1.840.0.e42a4c844b4cc9927c5ab76155b01045eba9d83f.001.1", "ENDS": "2022-01-10T00:45:00-05:00", "EVENT": "0010", "EXPIRATION": "2022-01-10T00:45:00-05:00", "ISSUANCE": "2022-01-10T00:00:00-05:00", "MSG_TYPE": "SMW", "ONSET": "2022-01-10T00:00:00-05:00", "PHENOM": "MA", "PROD_TYPE": "Special Marine Warning", "SIG": "W", "URL": "https://alerts-v2.weather.gov/#/?id=urn:oid:2.49.0.1.840.0.e42a4c844b4cc9927c5ab76155b01045eba9d83f.001.1", "VTEC": "/O.NEW.KTAE.MA.W.0010.220110T0500Z-220110T0545Z/", "WFO": "KTAE"}, "type": "Feature"}], "type": "FeatureCollection"}
