{"features": [{"geometry": {"coordinates": [[[-77.24, 38.67], [-77.22, 38.66], [-77.19, 38.66], [-77.19, 38.64], [-77.16, 38.65], [-77.2, 38.7], [-77.06, 38.73], [-77.08, 38.9], [-77.05, 38.91], [-77.0, 38.85], [-77.0, 38.7], [-77.08, 38.67], [-77.09, 38.62], [-77.17, 38.56], [-77.29, 38.58], [-77.24, 38.67]]], "type": "Polygon"}, "properties": {"CAP_ID": "urn:oid:2.49.0.1.840.0.23eabfaa932274ef875ef9202c5f2603357b0daa.001.1", "ENDS": "2021-10-17T15:15:00-04:00", "EVENT": "0332", "EXPIRATION": "2021-10-17T15:15:00-04:00", "ISSUANCE": "2021-10-17T13:12:00-04:00", "MSG_TYPE": "SMW", "ONSET": "2021-10-17T13:12:00-04:00", "PHENOM": "MA", "PROD_TYPE": "Special Marine Warning", "SIG": "W", "URL": "https://alerts-v2.weather.gov/#/?id=urn:oid:2.49.0.1.840.0.23eabfaa932274ef875ef9202c5f2603357b0daa.001.1", "VTEC": "/O.NEW.KLWX.MA.W.0332.211017T1712Z-211017T1915Z/", "WFO": "KLWX"}, "type": "Feature"}, {"geometry": {"coordinates": [[[-82.52, 41.62], [-82.46, 41.68], [-82.37, 41.69], [-81.92, 41.9], [-81.51, 41.77], [-81.5, 41.74], [-81.46, 41.76], [-81.27, 41.7], [-81.6, 41.5], [-81.61, 41.42], [-82.52, 41.62]]], "type": "Polygon"}, "properties": {"CAP_ID": "urn:oid:2.49.0.1.840.0.d3f8bb7569082d047ba25e34088c620fe7b44067.001.1", "ENDS": "2021-10-17T14:30:00-04:00", "EVENT": "0098", "EXPIRATION": "2021-10-17T14:30:00-04:00", "ISSUANCE": "2021-10-17T12:59:00-04:00", "MSG_TYPE": "SMW", "ONSET": "2021-10-17T12:59:00-04:00", "PHENOM": "MA", "PROD_TYPE": "Special Marine Warning", "SIG": "W", "URL": "https://alerts-v2.weather.gov/#/?id=urn:oid:2.49.0.1.840.0.d3f8bb7569082d047ba25e34088c620fe7b44067.001.1", "VTEC": "/O.NEW.KCLE.MA.W.0098.211017T1659Z-211017T1830Z/", "WFO": "KCLE"}, "type": "Feature"}], "type": "FeatureCollection"}
