{"features": [{"geometry": {"coordinates": [[[-83.81, 30.37], [-83.85, 30.39], [-83.88, 30.43], [-83.85, 30.47], [-83.75, 30.5], [-83.69, 30.53], [-83.63, 30.54], [-83.55, 30.53], [-83.51, 30.46], [-83.62, 30.43], [-83.68, 30.4], [-83.76, 30.4], [-83.81, 30.37]]], "type": "Polygon"}, "properties": {"CAP_ID": "urn:oid:2.49.0.1.840.0.91bd9d9cb7b3815264e8d01dd311bf698ebb3125.001.1", "ENDS": "2022-08-28T02:15:00-04:00", "EVENT": "0043", "EXPIRATION": "2022-08-28T02:15:00-04:00", "ISSUANCE": "2022-08-28T01:22:00-04:00", "MSG_TYPE": "FFS", "ONSET": "2022-08-28T01:22:00-04:00", "PHENOM": "FF", "PROD_TYPE": "Flash Flood Warning", "SIG": "W", "URL": "https://alerts-v2.weather.gov/#/?id=urn:oid:2.49.0.1.840.0.91bd9d9cb7b3815264e8d01dd311bf698ebb3125.001.1", "VTEC": "/O.CON.KTAE.FF.W.0043.000000T0000Z-220828T0615Z/", "WFO": "KTAE"}, "type": "Feature"}, {"geometry": {"coordinates": [[[-111.97, 31.82], [-111.86, 31.82], [-111.83, 31.71], [-111.94, 31.7], [-111.97, 31.82]]], "type": "Polygon"}, "properties": {"CAP_ID": "urn:oid:2.49.0.1.840.0.219cdbb4f2852d9775c2ad058b454261cd9e71a8.001.1", "ENDS": "2022-08-27T23:45:00-07:00", "EVENT": "0132", "EXPIRATION": "2022-08-27T23:45:00-07:00", "ISSUANCE": "2022-08-27T20:39:00-07:00", "MSG_TYPE": "FFW", "ONSET": "2022-08-27T20:39:00-07:00", "PHENOM": "FF", "PROD_TYPE": "Flash Flood Warning", "SIG": "W", "URL": "https://alerts-v2.weather.gov/#/?id=urn:oid:2.49.0.1.840.0.219cdbb4f2852d9775c2ad058b454261cd9e71a8.001.1", "VTEC": "/O.NEW.KTWC.FF.W.0132.220828T0339Z-220828T0645Z/", "WFO": "KTWC"}, "type": "Feature"}], "type": "FeatureCollection"}
