{"features": [{"geometry": {"coordinates": [[[-94.12, 38.51], [-94.49, 38.61], [-94.46, 38.75], [-94.12, 38.74], [-94.13, 38.66], [-94.12, 38.65], [-94.12, 38.51]]], "type": "Polygon"}, "properties": {"CAP_ID": "urn:oid:2.49.0.1.840.0.864b869e1c56d373a3859920927bfdcc90ff8013.001.1", "ENDS": "2024-06-08T01:15:00-05:00", "EVENT": "0218", "EXPIRATION": "2024-06-08T01:15:00-05:00", "ISSUANCE": "2024-06-08T00:47:00-05:00", "MSG_TYPE": "SVS", "ONSET": "2024-06-08T00:47:00-05:00", "PHENOM": "SV", "PROD_TYPE": "Severe Thunderstorm Warning", "SIG": "W", "URL": "https://alerts.weather.gov/search?id=urn:oid:2.49.0.1.840.0.864b869e1c56d373a3859920927bfdcc90ff8013.001.1", "VTEC": "/O.CON.KEAX.SV.W.0218.000000T0000Z-240608T0615Z/", "WFO": "KEAX"}, "type": "Feature"}], "type": "FeatureCollection"}
