{"features": [{"geometry": {"coordinates": [[[-81.16, 30.02], [-81.18, 30.14], [-80.67, 30.21], [-80.68, 29.99], [-81.16, 30.02]]], "type": "Polygon"}, "properties": {"CAP_ID": "urn:oid:2.49.0.1.840.0.8d4d333f738765583d4e38eed26d4c3918108ff8.001.1", "ENDS": "2022-02-18T17:00:00-05:00", "EVENT": "0003", "EXPIRATION": "2022-02-18T17:00:00-05:00", "ISSUANCE": "2022-02-18T16:13:00-05:00", "MSG_TYPE": "SMW", "ONSET": "2022-02-18T16:13:00-05:00", "PHENOM": "MA", "PROD_TYPE": "Special Marine Warning", "SIG": "W", "URL": "https://alerts-v2.weather.gov/#/?id=urn:oid:2.49.0.1.840.0.8d4d333f738765583d4e38eed26d4c3918108ff8.001.1", "VTEC": "/O.NEW.KJAX.MA.W.0003.220218T2113Z-220218T2200Z/", "WFO": "KJAX"}, "type": "Feature"}], "type": "FeatureCollection"}
