{"features": [{"geometry": {"coordinates": [[[-81.34, 34.28], [-80.84, 34.33], [-80.75, 33.93], [-81.0, 33.87], [-81.0, 33.88], [-81.01, 33.88], [-81.02, 33.88], [-81.03, 33.87], [-81.04, 33.87], [-81.04, 33.86], [-81.2, 33.82], [-81.41, 34.16], [-81.48, 34.27], [-81.34, 34.28]]], "type": "Polygon"}, "properties": {"CAP_ID": "urn:oid:2.49.0.1.840.0.e396c7de92e43e475ec9767cf8b67868ace6b8d2.001.1", "ENDS": "2024-07-31T03:15:00-04:00", "EVENT": "0016", "EXPIRATION": "2024-07-31T03:15:00-04:00", "ISSUANCE": "2024-07-31T01:12:00-04:00", "MSG_TYPE": "FFW", "ONSET": "2024-07-31T01:12:00-04:00", "PHENOM": "FF", "PROD_TYPE": "Flash Flood Warning", "SIG": "W", "URL": "https://alerts.weather.gov/search?id=urn:oid:2.49.0.1.840.0.e396c7de92e43e475ec9767cf8b67868ace6b8d2.001.1", "VTEC": "/O.NEW.KCAE.FF.W.0016.240731T0512Z-240731T0715Z/", "WFO": "KCAE"}, "type": "Feature"}, {"geometry": {"coordinates": [[[-86.26, 35.75], [-86.27, 35.46], [-86.63, 35.51], [-86.6, 35.81], [-86.26, 35.75]]], "type": "Polygon"}, "properties": {"CAP_ID": "urn:oid:2.49.0.1.840.0.68cf7afd4bac0a7bf06c18ed6007a6681deed079.001.1", "ENDS": "2024-07-31T01:30:00-05:00", "EVENT": "0033", "EXPIRATION": "2024-07-31T01:30:00-05:00", "ISSUANCE": "2024-07-31T00:11:00-05:00", "MSG_TYPE": "FFW", "ONSET": "2024-07-31T00:11:00-05:00", "PHENOM": "FF", "PROD_TYPE": "Flash Flood Warning", "SIG": "W", "URL": "https://alerts.weather.gov/search?id=urn:oid:2.49.0.1.840.0.68cf7afd4bac0a7bf06c18ed6007a6681deed079.001.1", "VTEC": "/O.EXT.KOHX.FF.W.0033.000000T0000Z-240731T0630Z/", "WFO": "KOHX"}, "type": "Feature"}], "type": "FeatureCollection"}
