{"features": [{"geometry": {"coordinates": [[[-93.65, 31.38], [-93.7, 31.43], [-93.69, 31.44], [-93.7, 31.44], [-93.7, 31.45], [-93.71, 31.46], [-93.72, 31.46], [-93.54, 31.61], [-93.4, 31.43], [-93.65, 31.38]]], "type": "Polygon"}, "properties": {"CAP_ID": "urn:oid:2.49.0.1.840.0.4b3d14bfa7862cfa01af45c08c814831fdb878d2.002.1", "ENDS": "2022-01-09T04:45:00-06:00", "EVENT": "0002", "EXPIRATION": "2022-01-09T04:45:00-06:00", "ISSUANCE": "2022-01-09T04:12:00-06:00", "MSG_TYPE": "SVS", "ONSET": "2022-01-09T04:12:00-06:00", "PHENOM": "TO", "PROD_TYPE": "Tornado Warning", "SIG": "W", "URL": "https://alerts-v2.weather.gov/#/?id=urn:oid:2.49.0.1.840.0.4b3d14bfa7862cfa01af45c08c814831fdb878d2.002.1", "VTEC": "/O.CON.KSHV.TO.W.0002.000000T0000Z-220109T1045Z/", "WFO": "KSHV"}, "type": "Feature"}, {"geometry": {"coordinates": [[[-94.54, 30.49], [-94.6, 30.78], [-94.45, 31.04], [-94.06, 31.11], [-93.99, 31.14], [-94.17, 30.6], [-94.62, 30.19], [-94.73, 30.49], [-94.54, 30.49]]], "type": "Polygon"}, "properties": {"CAP_ID": "urn:oid:2.49.0.1.840.0.6234b53f889a5a92440bdaf8f170f00239d3d894.001.1", "ENDS": "2022-01-09T06:00:00-06:00", "EVENT": "0002", "EXPIRATION": "2022-01-09T06:00:00-06:00", "ISSUANCE": "2022-01-09T02:57:00-06:00", "MSG_TYPE": "FFW", "ONSET": "2022-01-09T02:57:00-06:00", "PHENOM": "FF", "PROD_TYPE": "Flash Flood Warning", "SIG": "W", "URL": "https://alerts-v2.weather.gov/#/?id=urn:oid:2.49.0.1.840.0.6234b53f889a5a92440bdaf8f170f00239d3d894.001.1", "VTEC": "/O.NEW.KLCH.FF.W.0002.220109T0857Z-220109T1200Z/", "WFO": "KLCH"}, "type": "Feature"}, {"geometry": {"coordinates": [[[-94.45, 31.05], [-94.27, 31.25], [-94.1, 31.57], [-93.74, 31.5], [-93.93, 31.16], [-94.04, 31.13], [-94.06, 31.11], [-94.45, 31.05]]], "type": "Polygon"}, "properties": {"CAP_ID": "urn:oid:2.49.0.1.840.0.ff574569f266fd58c96ccb4af2dcc0bffe1e6a87.001.1", "ENDS": "2022-01-09T05:45:00-06:00", "EVENT": "0001", "EXPIRATION": "2022-01-09T05:45:00-06:00", "ISSUANCE": "2022-01-09T02:46:00-06:00", "MSG_TYPE": "FFW", "ONSET": "2022-01-09T02:46:00-06:00", "PHENOM": "FF", "PROD_TYPE": "Flash Flood Warning", "SIG": "W", "URL": "https://alerts-v2.weather.gov/#/?id=urn:oid:2.49.0.1.840.0.ff574569f266fd58c96ccb4af2dcc0bffe1e6a87.001.1", "VTEC": "/O.NEW.KSHV.FF.W.0001.220109T0846Z-220109T1145Z/", "WFO": "KSHV"}, "type": "Feature"}], "type": "FeatureCollection"}
