{"features": [{"geometry": {"coordinates": [[[-95.87, 40.85], [-96.22, 40.81], [-96.28, 41.01], [-96.0, 41.1], [-95.87, 40.85]]], "type": "Polygon"}, "properties": {"CAP_ID": "urn:oid:2.49.0.1.840.0.7e5484a0eda418c950a549600f8d9f96edf5ce9e.001.1", "ENDS": "2024-07-02T01:15:00-05:00", "EVENT": "0312", "EXPIRATION": "2024-07-02T01:15:00-05:00", "ISSUANCE": "2024-07-02T00:50:00-05:00", "MSG_TYPE": "SVS", "ONSET": "2024-07-02T00:50:00-05:00", "PHENOM": "SV", "PROD_TYPE": "Severe Thunderstorm Warning", "SIG": "W", "URL": "https://alerts.weather.gov/search?id=urn:oid:2.49.0.1.840.0.7e5484a0eda418c950a549600f8d9f96edf5ce9e.001.1", "VTEC": "/O.CON.KOAX.SV.W.0312.000000T0000Z-240702T0615Z/", "WFO": "KOAX"}, "type": "Feature"}, {"geometry": {"coordinates": [[[-97.04, 40.8], [-96.88, 40.9], [-96.83, 40.88], [-96.82, 40.8], [-96.78, 40.75], [-96.83, 40.73], [-96.91, 40.7], [-97.03, 40.64], [-97.14, 40.61], [-97.25, 40.61], [-97.23, 40.69], [-97.13, 40.75], [-97.04, 40.8]]], "type": "Polygon"}, "properties": {"CAP_ID": "urn:oid:2.49.0.1.840.0.ddf32a609927fb03876b97947f3425cc5a145c1e.001.1", "ENDS": "2024-07-02T04:00:00-05:00", "EVENT": "0032", "EXPIRATION": "2024-07-02T04:00:00-05:00", "ISSUANCE": "2024-07-01T23:54:00-05:00", "MSG_TYPE": "FFW", "ONSET": "2024-07-01T23:54:00-05:00", "PHENOM": "FF", "PROD_TYPE": "Flash Flood Warning", "SIG": "W", "URL": "https://alerts.weather.gov/search?id=urn:oid:2.49.0.1.840.0.ddf32a609927fb03876b97947f3425cc5a145c1e.001.1", "VTEC": "/O.NEW.KOAX.FF.W.0032.240702T0454Z-240702T0900Z/", "WFO": "KOAX"}, "type": "Feature"}, {"geometry": {"coordinates": [[[-96.56, 40.82], [-96.6, 40.73], [-96.71, 40.72], [-96.79, 40.75], [-96.83, 40.8], [-96.83, 40.87], [-96.75, 40.91], [-96.6, 40.92], [-96.57, 40.89], [-96.56, 40.82]]], "type": "Polygon"}, "properties": {"CAP_ID": "urn:oid:2.49.0.1.840.0.2096ac486392dc4c8ebe02df72fbc7e9a8777892.001.1", "ENDS": "2024-07-02T02:45:00-05:00", "EVENT": "0030", "EXPIRATION": "2024-07-02T02:45:00-05:00", "ISSUANCE": "2024-07-01T23:50:00-05:00", "MSG_TYPE": "FFS", "ONSET": "2024-07-01T23:50:00-05:00", "PHENOM": "FF", "PROD_TYPE": "Flash Flood Warning", "SIG": "W", "URL": "https://alerts.weather.gov/search?id=urn:oid:2.49.0.1.840.0.2096ac486392dc4c8ebe02df72fbc7e9a8777892.001.1", "VTEC": "/O.CON.KOAX.FF.W.0030.000000T0000Z-240702T0745Z/", "WFO": "KOAX"}, "type": "Feature"}, {"geometry": {"coordinates": [[[-96.37, 41.23], [-96.18, 41.39], [-95.89, 41.39], [-95.75, 41.3], [-95.81, 41.16], [-95.88, 41.16], [-95.86, 41.09], [-95.88, 41.05], [-95.96, 41.06], [-95.99, 41.05], [-96.06, 41.07], [-96.21, 40.99], [-96.25, 41.02], [-96.28, 41.02], [-96.33, 41.1], [-96.31, 41.11], [-96.32, 41.18], [-96.35, 41.21], [-96.37, 41.23]]], "type": "Polygon"}, "properties": {"CAP_ID": "urn:oid:2.49.0.1.840.0.7f8649fcf292a48718f45f6704804f516cd995bf.001.1", "ENDS": "2024-07-02T04:15:00-05:00", "EVENT": "0031", "EXPIRATION": "2024-07-02T04:15:00-05:00", "ISSUANCE": "2024-07-01T23:14:00-05:00", "MSG_TYPE": "FFW", "ONSET": "2024-07-01T23:14:00-05:00", "PHENOM": "FF", "PROD_TYPE": "Flash Flood Warning", "SIG": "W", "URL": "https://alerts.weather.gov/search?id=urn:oid:2.49.0.1.840.0.7f8649fcf292a48718f45f6704804f516cd995bf.001.1", "VTEC": "/O.NEW.KOAX.FF.W.0031.240702T0414Z-240702T0915Z/", "WFO": "KOAX"}, "type": "Feature"}], "type": "FeatureCollection"}
