{"features": [{"geometry": {"coordinates": [[[-95.19, 36.58], [-95.42, 36.37], [-95.88, 36.77], [-95.78, 37.0], [-95.66, 37.0], [-95.47, 36.94], [-95.19, 36.58]]], "type": "Polygon"}, "properties": {"CAP_ID": "urn:oid:2.49.0.1.840.0.04880623e78fb3d9da9c82a80182db4bbcf9ce51.001.1", "ENDS": "2022-05-15T02:00:00-05:00", "EVENT": "0186", "EXPIRATION": "2022-05-15T02:00:00-05:00", "ISSUANCE": "2022-05-15T01:12:00-05:00", "MSG_TYPE": "SVR", "ONSET": "2022-05-15T01:12:00-05:00", "PHENOM": "SV", "PROD_TYPE": "Severe Thunderstorm Warning", "SIG": "W", "URL": "https://alerts-v2.weather.gov/#/?id=urn:oid:2.49.0.1.840.0.04880623e78fb3d9da9c82a80182db4bbcf9ce51.001.1", "VTEC": "/O.NEW.KTSA.SV.W.0186.220515T0612Z-220515T0700Z/", "WFO": "KTSA"}, "type": "Feature"}, {"geometry": {"coordinates": [[[-89.1, 36.97], [-89.14, 36.99], [-89.17, 37.01], [-89.18, 37.02], [-89.18, 37.07], [-89.12, 37.09], [-89.01, 37.06], [-88.98, 36.97], [-89.06, 36.96], [-89.1, 36.97]]], "type": "Polygon"}, "properties": {"CAP_ID": "urn:oid:2.49.0.1.840.0.a7378eb36c0c94ea12cac1aa571a0fe6fa7be9cd.002.1", "ENDS": "2022-05-15T01:30:00-05:00", "EVENT": "0073", "EXPIRATION": "2022-05-15T01:30:00-05:00", "ISSUANCE": "2022-05-15T01:12:00-05:00", "MSG_TYPE": "SVS", "ONSET": "2022-05-15T01:12:00-05:00", "PHENOM": "SV", "PROD_TYPE": "Severe Thunderstorm Warning", "SIG": "W", "URL": "https://alerts-v2.weather.gov/#/?id=urn:oid:2.49.0.1.840.0.a7378eb36c0c94ea12cac1aa571a0fe6fa7be9cd.002.1", "VTEC": "/O.CON.KPAH.SV.W.0073.000000T0000Z-220515T0630Z/", "WFO": "KPAH"}, "type": "Feature"}, {"geometry": {"coordinates": [[[-95.0, 36.45], [-95.0, 36.4], [-95.31, 36.22], [-95.44, 36.34], [-95.43, 36.39], [-95.2, 36.62], [-95.0, 36.45]]], "type": "Polygon"}, "properties": {"CAP_ID": "urn:oid:2.49.0.1.840.0.08128b26a2083c10ef15b9b5dbe9cbf1274fd310.001.1", "ENDS": "2022-05-15T01:45:00-05:00", "EVENT": "0185", "EXPIRATION": "2022-05-15T01:45:00-05:00", "ISSUANCE": "2022-05-15T01:07:00-05:00", "MSG_TYPE": "SVR", "ONSET": "2022-05-15T01:07:00-05:00", "PHENOM": "SV", "PROD_TYPE": "Severe Thunderstorm Warning", "SIG": "W", "URL": "https://alerts-v2.weather.gov/#/?id=urn:oid:2.49.0.1.840.0.08128b26a2083c10ef15b9b5dbe9cbf1274fd310.001.1", "VTEC": "/O.NEW.KTSA.SV.W.0185.220515T0607Z-220515T0645Z/", "WFO": "KTSA"}, "type": "Feature"}, {"geometry": {"coordinates": [[[-88.16, 30.22], [-87.95, 29.72], [-88.2, 29.67], [-88.31, 29.88], [-88.36, 30.16], [-88.16, 30.22]]], "type": "Polygon"}, "properties": {"CAP_ID": "urn:oid:2.49.0.1.840.0.833629a1abcb85834cf49431838381fc7ad20631.001.1", "ENDS": "2022-05-15T02:30:00-05:00", "EVENT": "0113", "EXPIRATION": "2022-05-15T02:30:00-05:00", "ISSUANCE": "2022-05-15T00:26:00-05:00", "MSG_TYPE": "SMW", "ONSET": "2022-05-15T00:26:00-05:00", "PHENOM": "MA", "PROD_TYPE": "Special Marine Warning", "SIG": "W", "URL": "https://alerts-v2.weather.gov/#/?id=urn:oid:2.49.0.1.840.0.833629a1abcb85834cf49431838381fc7ad20631.001.1", "VTEC": "/O.NEW.KMOB.MA.W.0113.220515T0526Z-220515T0730Z/", "WFO": "KMOB"}, "type": "Feature"}], "type": "FeatureCollection"}
