{"features": [{"geometry": {"coordinates": [[[-101.78, 31.08], [-101.77, 31.3], [-101.58, 31.3], [-101.57, 31.08], [-101.78, 31.08]]], "type": "Polygon"}, "properties": {"CAP_ID": "urn:oid:2.49.0.1.840.0.080339d0efe329075ad113bc4e24827ab88a2b12.001.1", "ENDS": "2022-06-28T01:30:00-05:00", "EVENT": "0012", "EXPIRATION": "2022-06-28T01:30:00-05:00", "ISSUANCE": "2022-06-27T22:25:00-05:00", "MSG_TYPE": "FFW", "ONSET": "2022-06-27T22:25:00-05:00", "PHENOM": "FF", "PROD_TYPE": "Flash Flood Warning", "SIG": "W", "URL": "https://alerts-v2.weather.gov/#/?id=urn:oid:2.49.0.1.840.0.080339d0efe329075ad113bc4e24827ab88a2b12.001.1", "VTEC": "/O.NEW.KMAF.FF.W.0012.220628T0325Z-220628T0630Z/", "WFO": "KMAF"}, "type": "Feature"}], "type": "FeatureCollection"}
