{"features": [{"geometry": {"coordinates": [[[-80.5, 40.78], [-80.51, 40.78], [-80.51, 40.88], [-80.24, 41.03], [-80.11, 41.07], [-80.05, 40.87], [-80.41, 40.75], [-80.5, 40.78]]], "type": "Polygon"}, "properties": {"CAP_ID": "urn:oid:2.49.0.1.840.0.4aa68918df94edc2c99cb813b22c52923fb55cf3.002.1", "ENDS": "2022-02-19T08:30:00-05:00", "EVENT": "0002", "EXPIRATION": "2022-02-19T08:30:00-05:00", "ISSUANCE": "2022-02-19T08:17:00-05:00", "MSG_TYPE": "SQW", "ONSET": "2022-02-19T08:17:00-05:00", "PHENOM": "SQ", "PROD_TYPE": "Snow Squall Warning", "SIG": "W", "URL": "https://alerts-v2.weather.gov/#/?id=urn:oid:2.49.0.1.840.0.4aa68918df94edc2c99cb813b22c52923fb55cf3.002.1", "VTEC": "/O.CON.KPBZ.SQ.W.0002.000000T0000Z-220219T1330Z/", "WFO": "KPBZ"}, "type": "Feature"}, {"geometry": {"coordinates": [[[-80.13, 41.18], [-80.03, 41.34], [-79.79, 41.5], [-79.55, 41.49], [-79.51, 41.41], [-79.4, 41.22], [-79.74, 41.09], [-80.13, 41.18]]], "type": "Polygon"}, "properties": {"CAP_ID": "urn:oid:2.49.0.1.840.0.0bfa1aad60a89991c945cd80ab75b9264bc7724a.001.1", "ENDS": "2022-02-19T08:45:00-05:00", "EVENT": "0003", "EXPIRATION": "2022-02-19T08:45:00-05:00", "ISSUANCE": "2022-02-19T08:13:00-05:00", "MSG_TYPE": "SQW", "ONSET": "2022-02-19T08:13:00-05:00", "PHENOM": "SQ", "PROD_TYPE": "Snow Squall Warning", "SIG": "W", "URL": "https://alerts-v2.weather.gov/#/?id=urn:oid:2.49.0.1.840.0.0bfa1aad60a89991c945cd80ab75b9264bc7724a.001.1", "VTEC": "/O.NEW.KPBZ.SQ.W.0003.220219T1313Z-220219T1345Z/", "WFO": "KPBZ"}, "type": "Feature"}], "type": "FeatureCollection"}
